sonicsynth/__init__.py
sonicsynth/composition.py
sonicsynth/dsp_effects.py
sonicsynth/envelope.py
sonicsynth/export.py
sonicsynth/playback.py
sonicsynth/wave_generator.py
sonicsynth-1.0.0.dist-info/LICENSE
sonicsynth-1.0.0.dist-info/METADATA
sonicsynth-1.0.0.dist-info/WHEEL
sonicsynth-1.0.0.dist-info/top_level.txt
sonicsynth-1.0.0.dist-info/RECORD
