Metadata-Version: 2.1
Name: sonicsynth
Version: 1.0.0
Summary: An audio synthesis library for sound generation and manipulation
Home-page: https://github.com/Frikallo/sonicsynth
Author: Noah Kay
Author-email: noahkay13@gmail.com
License: UNKNOWN
Platform: UNKNOWN
Classifier: Development Status :: 5 - Production/Stable
Classifier: Intended Audience :: Developers
Classifier: License :: OSI Approved :: MIT License
Classifier: Operating System :: OS Independent
Classifier: Programming Language :: Python
Classifier: Programming Language :: Python :: 3
Classifier: Programming Language :: Python :: 3.6
Classifier: Programming Language :: Python :: 3.7
Classifier: Programming Language :: Python :: 3.8
Classifier: Programming Language :: Python :: 3.9
Classifier: Programming Language :: Python :: 3.10
Classifier: Topic :: Multimedia :: Sound/Audio
License-File: LICENSE
Requires-Dist: numpy
Requires-Dist: scipy
Requires-Dist: pydub
